{"cross_post": ["facebook_business", "tumblr", "medium", "discord", "telegram", "taggr", "twitter", "bluesky", "mastadon", "threads", "instagram"], "host": "github.com", "user": "oomlout", "allotment_name": "the_allotment_oomlout", "beet": "Working on my Japanese department style wrapping! Currently cursing the rounded corners on pencil crayon tins, and a legacy roll of relatively thick kraft paper.", "time": "2024-11-21 13:55:58", "time_beet": "2024/11/21/13_55_58", "folder": "github.com/oomlout/the_allotment_oomlout/2024/11/21/13_55_58", "id": "github_com_oomlout_the_allotment_oomlout_2024_11_21_13_55_58"}